ckanext_usmetadata-0.3.3-nspkg.pth
ckanext/usmetadata/blueprint.py
ckanext/usmetadata/db_utils.py
ckanext/usmetadata/helper.py
ckanext/usmetadata/media_types.json
ckanext/usmetadata/plugin.py
ckanext/usmetadata/resource_formats.json
ckanext/usmetadata/fanstatic/add_subagency.js
ckanext/usmetadata/fanstatic/dataset_edit_form.js
ckanext/usmetadata/fanstatic/dataset_url.js
ckanext/usmetadata/fanstatic/redactions.js
ckanext/usmetadata/fanstatic/resource_form.css
ckanext/usmetadata/fanstatic/resource_form.js
ckanext/usmetadata/fanstatic/webassets.yml
ckanext/usmetadata/public/redacted_icon.png
ckanext/usmetadata/public/redaction_clear.png
ckanext/usmetadata/public/base/images/inventory-logo.png
ckanext/usmetadata/templates/base.html
ckanext/usmetadata/templates/footer.html
ckanext/usmetadata/templates/organization/activity_stream.html
ckanext/usmetadata/templates/organization/member_new.html
ckanext/usmetadata/templates/organization/read_base.html
ckanext/usmetadata/templates/package/base.html
ckanext/usmetadata/templates/package/read.html
ckanext/usmetadata/templates/package/read_base.html
ckanext/usmetadata/templates/package/resource_read.html
ckanext/usmetadata/templates/package/snippets/expanded_common_core_fields.html
ckanext/usmetadata/templates/package/snippets/info.html
ckanext/usmetadata/templates/package/snippets/metadata_info.html
ckanext/usmetadata/templates/package/snippets/package_basic_fields.html
ckanext/usmetadata/templates/package/snippets/package_form.html
ckanext/usmetadata/templates/package/snippets/package_metadata_fields.html
ckanext/usmetadata/templates/package/snippets/required_common_core_fields.html
ckanext/usmetadata/templates/package/snippets/required_if_applicable_common_core_fields.html
ckanext/usmetadata/templates/package/snippets/resource_form.html
ckanext/usmetadata/templates/package/snippets/resource_item.html
ckanext/usmetadata/templates/package/snippets/resources.html
ckanext/usmetadata/templates/package/snippets/stages.html
ckanext_usmetadata-0.3.3.dist-info/METADATA
ckanext_usmetadata-0.3.3.dist-info/WHEEL
ckanext_usmetadata-0.3.3.dist-info/entry_points.txt
ckanext_usmetadata-0.3.3.dist-info/namespace_packages.txt
ckanext_usmetadata-0.3.3.dist-info/top_level.txt
ckanext_usmetadata-0.3.3.dist-info/RECORD
