Metadata-Version: 2.1
Name: ckanext-usmetadata
Version: 0.3.3
Summary: US Metadata Plugin for CKAN
Home-page: https://github.com/GSA/ckanext-usmetadata
Author: Data.gov
Author-email: datagovhelp@gsa.gov
License: Public Domain
Classifier: Programming Language :: Python :: 3
